interferometer/__init__.py
interferometer/main.py
interferometer-1.1.1.dist-info/LICENSE
interferometer-1.1.1.dist-info/METADATA
interferometer-1.1.1.dist-info/WHEEL
interferometer-1.1.1.dist-info/top_level.txt
interferometer-1.1.1.dist-info/RECORD
