Metadata-Version: 2.1
Name: interferometer
Version: 1.1.1
Summary: Algorithms for universal interferometers
Author-email: "William R. Clements" <mail@william-clements.com>
Project-URL: Homepage, https://github.com/clementsw/interferometer
Project-URL: Bug Tracker, https://github.com/clementsw/interferometer/issues
Classifier: Development Status :: 5 - Production/Stable
Classifier: Programming Language :: Python :: 3
Classifier: License :: OSI Approved :: MIT License
Classifier: Operating System :: OS Independent
Classifier: Topic :: Scientific/Engineering :: Physics
Requires-Python: >=3.7
License-File: LICENSE
Requires-Dist: numpy
Requires-Dist: matplotlib
